wsl_windows_toolbar/__init__.py
wsl_windows_toolbar/wsl-windows-toolbar-template.bat.j2
wsl_windows_toolbar/wsl-windows-toolbar-template.sh.j2
wsl_windows_toolbar/wsl_windows_toolbar.py
wsl_windows_toolbar-0.6.3.dist-info/LICENSE
wsl_windows_toolbar-0.6.3.dist-info/METADATA
wsl_windows_toolbar-0.6.3.dist-info/WHEEL
wsl_windows_toolbar-0.6.3.dist-info/entry_points.txt
wsl_windows_toolbar-0.6.3.dist-info/top_level.txt
wsl_windows_toolbar-0.6.3.dist-info/RECORD
