Metadata-Version: 2.1
Name: wsl-windows-toolbar
Version: 0.6.3
Summary: Adds linux GUI application menu to a windows toolbar
Home-page: https://github.com/cascadium/wsl-windows-toolbar-launcher
Author: Frank Quinn
Author-email: fquinn@cascadium.io
License: UNKNOWN
Platform: UNKNOWN
Requires-Python: >=3
Requires-Dist: click (>=7)
Requires-Dist: pyxdg (>=0.26)
Requires-Dist: winshell (>=0.6)
Requires-Dist: swinlnk (>=0.1.4)
Requires-Dist: pillow (>=6)
Requires-Dist: python-magic (>=0.4.15)
Requires-Dist: jinja2 (>=2.11)
